<?xml version="1.0" encoding="utf-8"?>
<hibernate-mapping assembly="Entities.EnquiryEntities" namespace="Entities.EnquiryEntities" xmlns="urn:nhibernate-mapping-2.2">
  <class name="Entities.EnquiryEntities.EnquiryCourseBatchTiming,Entities" table="EnquiryCourseBatchTiming" lazy="true" >
    <id name="Id" column="Id" type="Int64">
      <generator class="native" />
    </id>
    <property name="Batch">
      <column name="Batch" sql-type="nvarchar" not-null="false" />
    </property>
    <property name="Timing">
      <column name="Timing" sql-type="nvarchar" not-null="false" />
    </property>
    <property name="EnquiryCourseId">
      <column name="EnquiryCourseId" sql-type="Int64" not-null="false" />
    </property>
    <property name="EnquiryId">
      <column name="EnquiryId" sql-type="Int64" not-null="false" />
    </property>
    <property name="CreatedBy">
      <column name="CreatedBy" sql-type="nvarchar" not-null="false" />
    </property>
    <property name="CreatedDate">
      <column name="CreatedDate" sql-type="DateTime" not-null="false" />
    </property>
    <property name="ModifiedBy">
      <column name="ModifiedBy" sql-type="nvarchar" not-null="false" />
    </property>
    <property name="ModifiedDate">
      <column name="ModifiedDate" sql-type="DateTime" not-null="false" />
    </property>
    <property name="BatchId">
      <column name="BatchId" sql-type="Int64" not-null="false" />
    </property>
    <property name="TimingId">
      <column name="TimingId" sql-type="Int64" not-null="false" />
    </property>
  </class>
</hibernate-mapping>