<?xml version="1.0" encoding="utf-8" ?>

<hibernate-mapping assembly="TIPS.Entities.AdmissionEntities.PastSchoolDetails" namespace="TIPS.Entities.AdmissionEntities" xmlns="urn:nhibernate-mapping-2.2">
  <class name="TIPS.Entities.AdmissionEntities.LocationCount_Vw, TIPS.Entities" table="LocationCount_Vw" lazy="false" >
    <id name="Id" column="Id" type="Int64">
      <generator class="identity"></generator>
    </id>
    <property name="Campus" column="Campus" type="string"></property>
    <property name="LocationCount" column="LocationCount" type="int"></property>
    <property name="Locality" column="Locality" type="string"></property>
  </class>
</hibernate-mapping>
